pytest_mitmproxy/__init__.py
pytest_mitmproxy/addon.py
pytest_mitmproxy/install_cert.py
pytest_mitmproxy/plugin.py
pytest_mitmproxy/system_proxy.py
pytest_mitmproxy-1.0.7.dist-info/METADATA
pytest_mitmproxy-1.0.7.dist-info/WHEEL
pytest_mitmproxy-1.0.7.dist-info/entry_points.txt
pytest_mitmproxy-1.0.7.dist-info/top_level.txt
pytest_mitmproxy-1.0.7.dist-info/RECORD
