Metadata-Version: 2.1
Name: pytest-mitmproxy
Version: 1.0.7
Summary: pytest plugin for mitmproxy tests
Author-email: funcdefmain <741132517@qq.com>
License: MIT
Requires-Python: >=3.10
Requires-Dist: pytest>=7.0
Requires-Dist: mitmproxy>=10.0
Requires-Dist: psutil>=5.0
